{
  "config": "{\"version\": \"5.58\", \"themeCollection\": {\"customTheme\": {\"name\": \"Retail Corporate Dark Blue\", \"path\": \"../../theme_retail_corporate.json\"}}}",
  "layoutOptimization": 0,
  "sections": [
    {
      "name": "ExecutiveOverview",
      "displayName": "Executive Overview",
      "width": 1280,
      "height": 720,
      "visualContainers": [
        {
          "config": "{\"name\": \"12663093-b4e3-4e09-a19c-2e1d3e99ab5f\", \"layouts\": [{\"id\": 0, \"position\": {\"x\": 20, \"y\": 30, \"z\": 0, \"width\": 210, \"height\": 95, \"tabOrder\": 0}}], \"singleVisual\": {\"visualType\": \"card\", \"projections\": {\"Values\": [{\"queryRef\": \"Sales.Total Revenue\"}]}, \"prototypeQuery\": {\"Version\": 2, \"From\": [{\"Name\": \"s\", \"Entity\": \"Sales\", \"Type\": 0}], \"Select\": [{\"Measure\": {\"Expression\": {\"SourceRef\": {\"Source\": \"s\"}}, \"Property\": \"Total Revenue\"}, \"Name\": \"Sales.Total Revenue\", \"NativeReferenceName\": \"Total Revenue\"}]}, \"drillFilterOtherVisuals\": true, \"hasDefaultSort\": true, \"objects\": {}, \"vcObjects\": {\"title\": [{\"properties\": {\"text\": {\"expr\": {\"Literal\": {\"Value\": \"'Revenue'\"}}}, \"show\": {\"expr\": {\"Literal\": {\"Value\": \"true\"}}}}}]}}}",
          "query": "{\"Version\": 2, \"From\": [{\"Name\": \"s\", \"Entity\": \"Sales\", \"Type\": 0}], \"Select\": [{\"Measure\": {\"Expression\": {\"SourceRef\": {\"Source\": \"s\"}}, \"Property\": \"Total Revenue\"}, \"Name\": \"Sales.Total Revenue\", \"NativeReferenceName\": \"Total Revenue\"}]}",
          "dataTransforms": "{}"
        },
        {
          "config": "{\"name\": \"f25ef30e-d772-4c81-91fe-b42df31355a5\", \"layouts\": [{\"id\": 0, \"position\": {\"x\": 250, \"y\": 30, \"z\": 1, \"width\": 210, \"height\": 95, \"tabOrder\": 1}}], \"singleVisual\": {\"visualType\": \"card\", \"projections\": {\"Values\": [{\"queryRef\": \"Sales.Total Profit\"}]}, \"prototypeQuery\": {\"Version\": 2, \"From\": [{\"Name\": \"s\", \"Entity\": \"Sales\", \"Type\": 0}], \"Select\": [{\"Measure\": {\"Expression\": {\"SourceRef\": {\"Source\": \"s\"}}, \"Property\": \"Total Profit\"}, \"Name\": \"Sales.Total Profit\", \"NativeReferenceName\": \"Total Profit\"}]}, \"drillFilterOtherVisuals\": true, \"hasDefaultSort\": true, \"objects\": {}, \"vcObjects\": {\"title\": [{\"properties\": {\"text\": {\"expr\": {\"Literal\": {\"Value\": \"'Profit'\"}}}, \"show\": {\"expr\": {\"Literal\": {\"Value\": \"true\"}}}}}]}}}",
          "query": "{\"Version\": 2, \"From\": [{\"Name\": \"s\", \"Entity\": \"Sales\", \"Type\": 0}], \"Select\": [{\"Measure\": {\"Expression\": {\"SourceRef\": {\"Source\": \"s\"}}, \"Property\": \"Total Profit\"}, \"Name\": \"Sales.Total Profit\", \"NativeReferenceName\": \"Total Profit\"}]}",
          "dataTransforms": "{}"
        },
        {
          "config": "{\"name\": \"fc4b68e3-1a4e-481a-9640-e382d04c9977\", \"layouts\": [{\"id\": 0, \"position\": {\"x\": 480, \"y\": 30, \"z\": 2, \"width\": 210, \"height\": 95, \"tabOrder\": 2}}], \"singleVisual\": {\"visualType\": \"card\", \"projections\": {\"Values\": [{\"queryRef\": \"Sales.Profit Margin\"}]}, \"prototypeQuery\": {\"Version\": 2, \"From\": [{\"Name\": \"s\", \"Entity\": \"Sales\", \"Type\": 0}], \"Select\": [{\"Measure\": {\"Expression\": {\"SourceRef\": {\"Source\": \"s\"}}, \"Property\": \"Profit Margin\"}, \"Name\": \"Sales.Profit Margin\", \"NativeReferenceName\": \"Profit Margin\"}]}, \"drillFilterOtherVisuals\": true, \"hasDefaultSort\": true, \"objects\": {}, \"vcObjects\": {\"title\": [{\"properties\": {\"text\": {\"expr\": {\"Literal\": {\"Value\": \"'Margin'\"}}}, \"show\": {\"expr\": {\"Literal\": {\"Value\": \"true\"}}}}}]}}}",
          "query": "{\"Version\": 2, \"From\": [{\"Name\": \"s\", \"Entity\": \"Sales\", \"Type\": 0}], \"Select\": [{\"Measure\": {\"Expression\": {\"SourceRef\": {\"Source\": \"s\"}}, \"Property\": \"Profit Margin\"}, \"Name\": \"Sales.Profit Margin\", \"NativeReferenceName\": \"Profit Margin\"}]}",
          "dataTransforms": "{}"
        },
        {
          "config": "{\"name\": \"1b8630d2-45b7-4057-86d1-63130abfd6f8\", \"layouts\": [{\"id\": 0, \"position\": {\"x\": 710, \"y\": 30, \"z\": 3, \"width\": 210, \"height\": 95, \"tabOrder\": 3}}], \"singleVisual\": {\"visualType\": \"card\", \"projections\": {\"Values\": [{\"queryRef\": \"Sales.Total Orders\"}]}, \"prototypeQuery\": {\"Version\": 2, \"From\": [{\"Name\": \"s\", \"Entity\": \"Sales\", \"Type\": 0}], \"Select\": [{\"Measure\": {\"Expression\": {\"SourceRef\": {\"Source\": \"s\"}}, \"Property\": \"Total Orders\"}, \"Name\": \"Sales.Total Orders\", \"NativeReferenceName\": \"Total Orders\"}]}, \"drillFilterOtherVisuals\": true, \"hasDefaultSort\": true, \"objects\": {}, \"vcObjects\": {\"title\": [{\"properties\": {\"text\": {\"expr\": {\"Literal\": {\"Value\": \"'Orders'\"}}}, \"show\": {\"expr\": {\"Literal\": {\"Value\": \"true\"}}}}}]}}}",
          "query": "{\"Version\": 2, \"From\": [{\"Name\": \"s\", \"Entity\": \"Sales\", \"Type\": 0}], \"Select\": [{\"Measure\": {\"Expression\": {\"SourceRef\": {\"Source\": \"s\"}}, \"Property\": \"Total Orders\"}, \"Name\": \"Sales.Total Orders\", \"NativeReferenceName\": \"Total Orders\"}]}",
          "dataTransforms": "{}"
        },
        {
          "config": "{\"name\": \"0a129fa4-c7ab-45ca-a2ec-386f6fdd9738\", \"layouts\": [{\"id\": 0, \"position\": {\"x\": 940, \"y\": 30, \"z\": 4, \"width\": 210, \"height\": 95, \"tabOrder\": 4}}], \"singleVisual\": {\"visualType\": \"card\", \"projections\": {\"Values\": [{\"queryRef\": \"Sales.Avg Order Value\"}]}, \"prototypeQuery\": {\"Version\": 2, \"From\": [{\"Name\": \"s\", \"Entity\": \"Sales\", \"Type\": 0}], \"Select\": [{\"Measure\": {\"Expression\": {\"SourceRef\": {\"Source\": \"s\"}}, \"Property\": \"Avg Order Value\"}, \"Name\": \"Sales.Avg Order Value\", \"NativeReferenceName\": \"Avg Order Value\"}]}, \"drillFilterOtherVisuals\": true, \"hasDefaultSort\": true, \"objects\": {}, \"vcObjects\": {\"title\": [{\"properties\": {\"text\": {\"expr\": {\"Literal\": {\"Value\": \"'AOV'\"}}}, \"show\": {\"expr\": {\"Literal\": {\"Value\": \"true\"}}}}}]}}}",
          "query": "{\"Version\": 2, \"From\": [{\"Name\": \"s\", \"Entity\": \"Sales\", \"Type\": 0}], \"Select\": [{\"Measure\": {\"Expression\": {\"SourceRef\": {\"Source\": \"s\"}}, \"Property\": \"Avg Order Value\"}, \"Name\": \"Sales.Avg Order Value\", \"NativeReferenceName\": \"Avg Order Value\"}]}",
          "dataTransforms": "{}"
        },
        {
          "config": "{\"name\": \"e00cc740-b2e6-46ce-82e9-b462f9854ab1\", \"layouts\": [{\"id\": 0, \"position\": {\"x\": 20, \"y\": 150, \"z\": 5, \"width\": 540, \"height\": 300, \"tabOrder\": 5}}], \"singleVisual\": {\"visualType\": \"lineChart\", \"projections\": {\"Category\": [{\"queryRef\": \"Date.Date\", \"active\": true}], \"Y\": [{\"queryRef\": \"Sales.Total Revenue\"}]}, \"prototypeQuery\": {\"Version\": 2, \"From\": [{\"Name\": \"s\", \"Entity\": \"Sales\", \"Type\": 0}, {\"Name\": \"d\", \"Entity\": \"Date\", \"Type\": 0}], \"Select\": [{\"Column\": {\"Expression\": {\"SourceRef\": {\"Source\": \"d\"}}, \"Property\": \"Date\"}, \"Name\": \"Date.Date\", \"NativeReferenceName\": \"Date\"}, {\"Measure\": {\"Expression\": {\"SourceRef\": {\"Source\": \"s\"}}, \"Property\": \"Total Revenue\"}, \"Name\": \"Sales.Total Revenue\", \"NativeReferenceName\": \"Total Revenue\"}]}, \"drillFilterOtherVisuals\": true, \"hasDefaultSort\": true, \"objects\": {}, \"vcObjects\": {\"title\": [{\"properties\": {\"text\": {\"expr\": {\"Literal\": {\"Value\": \"'Sales Trend'\"}}}, \"show\": {\"expr\": {\"Literal\": {\"Value\": \"true\"}}}}}]}}}",
          "query": "{\"Version\": 2, \"From\": [{\"Name\": \"s\", \"Entity\": \"Sales\", \"Type\": 0}, {\"Name\": \"d\", \"Entity\": \"Date\", \"Type\": 0}], \"Select\": [{\"Column\": {\"Expression\": {\"SourceRef\": {\"Source\": \"d\"}}, \"Property\": \"Date\"}, \"Name\": \"Date.Date\", \"NativeReferenceName\": \"Date\"}, {\"Measure\": {\"Expression\": {\"SourceRef\": {\"Source\": \"s\"}}, \"Property\": \"Total Revenue\"}, \"Name\": \"Sales.Total Revenue\", \"NativeReferenceName\": \"Total Revenue\"}]}",
          "dataTransforms": "{}"
        },
        {
          "config": "{\"name\": \"6ec29846-fc3b-480c-8b56-fe5e092a4918\", \"layouts\": [{\"id\": 0, \"position\": {\"x\": 590, \"y\": 150, \"z\": 6, \"width\": 560, \"height\": 300, \"tabOrder\": 6}}], \"singleVisual\": {\"visualType\": \"barChart\", \"projections\": {\"Category\": [{\"queryRef\": \"Sales.ProductCategory\", \"active\": true}], \"Y\": [{\"queryRef\": \"Sales.Total Revenue\"}]}, \"prototypeQuery\": {\"Version\": 2, \"From\": [{\"Name\": \"s\", \"Entity\": \"Sales\", \"Type\": 0}], \"Select\": [{\"Column\": {\"Expression\": {\"SourceRef\": {\"Source\": \"s\"}}, \"Property\": \"ProductCategory\"}, \"Name\": \"Sales.ProductCategory\", \"NativeReferenceName\": \"ProductCategory\"}, {\"Measure\": {\"Expression\": {\"SourceRef\": {\"Source\": \"s\"}}, \"Property\": \"Total Revenue\"}, \"Name\": \"Sales.Total Revenue\", \"NativeReferenceName\": \"Total Revenue\"}]}, \"drillFilterOtherVisuals\": true, \"hasDefaultSort\": true, \"objects\": {}, \"vcObjects\": {\"title\": [{\"properties\": {\"text\": {\"expr\": {\"Literal\": {\"Value\": \"'Revenue by Category'\"}}}, \"show\": {\"expr\": {\"Literal\": {\"Value\": \"true\"}}}}}]}}}",
          "query": "{\"Version\": 2, \"From\": [{\"Name\": \"s\", \"Entity\": \"Sales\", \"Type\": 0}], \"Select\": [{\"Column\": {\"Expression\": {\"SourceRef\": {\"Source\": \"s\"}}, \"Property\": \"ProductCategory\"}, \"Name\": \"Sales.ProductCategory\", \"NativeReferenceName\": \"ProductCategory\"}, {\"Measure\": {\"Expression\": {\"SourceRef\": {\"Source\": \"s\"}}, \"Property\": \"Total Revenue\"}, \"Name\": \"Sales.Total Revenue\", \"NativeReferenceName\": \"Total Revenue\"}]}",
          "dataTransforms": "{}"
        },
        {
          "config": "{\"name\": \"6e1b1b0b-c84c-4eb8-a40d-16e2c6a96a26\", \"layouts\": [{\"id\": 0, \"position\": {\"x\": 20, \"y\": 475, \"z\": 7, \"width\": 540, \"height\": 235, \"tabOrder\": 7}}], \"singleVisual\": {\"visualType\": \"treemap\", \"projections\": {\"Category\": [{\"queryRef\": \"Sales.Region\", \"active\": true}], \"Values\": [{\"queryRef\": \"Sales.Total Profit\"}]}, \"prototypeQuery\": {\"Version\": 2, \"From\": [{\"Name\": \"s\", \"Entity\": \"Sales\", \"Type\": 0}], \"Select\": [{\"Column\": {\"Expression\": {\"SourceRef\": {\"Source\": \"s\"}}, \"Property\": \"Region\"}, \"Name\": \"Sales.Region\", \"NativeReferenceName\": \"Region\"}, {\"Measure\": {\"Expression\": {\"SourceRef\": {\"Source\": \"s\"}}, \"Property\": \"Total Profit\"}, \"Name\": \"Sales.Total Profit\", \"NativeReferenceName\": \"Total Profit\"}]}, \"drillFilterOtherVisuals\": true, \"hasDefaultSort\": true, \"objects\": {}, \"vcObjects\": {\"title\": [{\"properties\": {\"text\": {\"expr\": {\"Literal\": {\"Value\": \"'Profit by Region'\"}}}, \"show\": {\"expr\": {\"Literal\": {\"Value\": \"true\"}}}}}]}}}",
          "query": "{\"Version\": 2, \"From\": [{\"Name\": \"s\", \"Entity\": \"Sales\", \"Type\": 0}], \"Select\": [{\"Column\": {\"Expression\": {\"SourceRef\": {\"Source\": \"s\"}}, \"Property\": \"Region\"}, \"Name\": \"Sales.Region\", \"NativeReferenceName\": \"Region\"}, {\"Measure\": {\"Expression\": {\"SourceRef\": {\"Source\": \"s\"}}, \"Property\": \"Total Profit\"}, \"Name\": \"Sales.Total Profit\", \"NativeReferenceName\": \"Total Profit\"}]}",
          "dataTransforms": "{}"
        },
        {
          "config": "{\"name\": \"44a846cf-51a1-4a62-9ea4-5eac2eea128e\", \"layouts\": [{\"id\": 0, \"position\": {\"x\": 590, \"y\": 475, \"z\": 8, \"width\": 560, \"height\": 235, \"tabOrder\": 8}}], \"singleVisual\": {\"visualType\": \"barChart\", \"projections\": {\"Category\": [{\"queryRef\": \"Sales.Segment\", \"active\": true}], \"Y\": [{\"queryRef\": \"Sales.Total Revenue\"}]}, \"prototypeQuery\": {\"Version\": 2, \"From\": [{\"Name\": \"s\", \"Entity\": \"Sales\", \"Type\": 0}], \"Select\": [{\"Column\": {\"Expression\": {\"SourceRef\": {\"Source\": \"s\"}}, \"Property\": \"Segment\"}, \"Name\": \"Sales.Segment\", \"NativeReferenceName\": \"Segment\"}, {\"Measure\": {\"Expression\": {\"SourceRef\": {\"Source\": \"s\"}}, \"Property\": \"Total Revenue\"}, \"Name\": \"Sales.Total Revenue\", \"NativeReferenceName\": \"Total Revenue\"}]}, \"drillFilterOtherVisuals\": true, \"hasDefaultSort\": true, \"objects\": {}, \"vcObjects\": {\"title\": [{\"properties\": {\"text\": {\"expr\": {\"Literal\": {\"Value\": \"'Revenue by Segment'\"}}}, \"show\": {\"expr\": {\"Literal\": {\"Value\": \"true\"}}}}}]}}}",
          "query": "{\"Version\": 2, \"From\": [{\"Name\": \"s\", \"Entity\": \"Sales\", \"Type\": 0}], \"Select\": [{\"Column\": {\"Expression\": {\"SourceRef\": {\"Source\": \"s\"}}, \"Property\": \"Segment\"}, \"Name\": \"Sales.Segment\", \"NativeReferenceName\": \"Segment\"}, {\"Measure\": {\"Expression\": {\"SourceRef\": {\"Source\": \"s\"}}, \"Property\": \"Total Revenue\"}, \"Name\": \"Sales.Total Revenue\", \"NativeReferenceName\": \"Total Revenue\"}]}",
          "dataTransforms": "{}"
        }
      ]
    },
    {
      "name": "ProductPerformance",
      "displayName": "Product Performance",
      "width": 1280,
      "height": 720,
      "visualContainers": [
        {
          "config": "{\"name\": \"ec72e662-0263-4454-ae6d-d34bf2a9ed60\", \"layouts\": [{\"id\": 0, \"position\": {\"x\": 20, \"y\": 30, \"z\": 0, \"width\": 650, \"height\": 650, \"tabOrder\": 0}}], \"singleVisual\": {\"visualType\": \"tableEx\", \"projections\": {\"Values\": [{\"queryRef\": \"Sales.ProductName\"}, {\"queryRef\": \"Sales.Total Revenue\"}, {\"queryRef\": \"Sales.Total Profit\"}, {\"queryRef\": \"Sales.Total Quantity\"}, {\"queryRef\": \"Sales.Profit Margin\"}]}, \"prototypeQuery\": {\"Version\": 2, \"From\": [{\"Name\": \"s\", \"Entity\": \"Sales\", \"Type\": 0}], \"Select\": [{\"Column\": {\"Expression\": {\"SourceRef\": {\"Source\": \"s\"}}, \"Property\": \"ProductName\"}, \"Name\": \"Sales.ProductName\", \"NativeReferenceName\": \"ProductName\"}, {\"Measure\": {\"Expression\": {\"SourceRef\": {\"Source\": \"s\"}}, \"Property\": \"Total Revenue\"}, \"Name\": \"Sales.Total Revenue\", \"NativeReferenceName\": \"Total Revenue\"}, {\"Measure\": {\"Expression\": {\"SourceRef\": {\"Source\": \"s\"}}, \"Property\": \"Total Profit\"}, \"Name\": \"Sales.Total Profit\", \"NativeReferenceName\": \"Total Profit\"}, {\"Measure\": {\"Expression\": {\"SourceRef\": {\"Source\": \"s\"}}, \"Property\": \"Total Quantity\"}, \"Name\": \"Sales.Total Quantity\", \"NativeReferenceName\": \"Total Quantity\"}, {\"Measure\": {\"Expression\": {\"SourceRef\": {\"Source\": \"s\"}}, \"Property\": \"Profit Margin\"}, \"Name\": \"Sales.Profit Margin\", \"NativeReferenceName\": \"Profit Margin\"}]}, \"drillFilterOtherVisuals\": true, \"hasDefaultSort\": true, \"objects\": {}, \"vcObjects\": {\"title\": [{\"properties\": {\"text\": {\"expr\": {\"Literal\": {\"Value\": \"'Top Products'\"}}}, \"show\": {\"expr\": {\"Literal\": {\"Value\": \"true\"}}}}}]}}}",
          "query": "{\"Version\": 2, \"From\": [{\"Name\": \"s\", \"Entity\": \"Sales\", \"Type\": 0}], \"Select\": [{\"Column\": {\"Expression\": {\"SourceRef\": {\"Source\": \"s\"}}, \"Property\": \"ProductName\"}, \"Name\": \"Sales.ProductName\", \"NativeReferenceName\": \"ProductName\"}, {\"Measure\": {\"Expression\": {\"SourceRef\": {\"Source\": \"s\"}}, \"Property\": \"Total Revenue\"}, \"Name\": \"Sales.Total Revenue\", \"NativeReferenceName\": \"Total Revenue\"}, {\"Measure\": {\"Expression\": {\"SourceRef\": {\"Source\": \"s\"}}, \"Property\": \"Total Profit\"}, \"Name\": \"Sales.Total Profit\", \"NativeReferenceName\": \"Total Profit\"}, {\"Measure\": {\"Expression\": {\"SourceRef\": {\"Source\": \"s\"}}, \"Property\": \"Total Quantity\"}, \"Name\": \"Sales.Total Quantity\", \"NativeReferenceName\": \"Total Quantity\"}, {\"Measure\": {\"Expression\": {\"SourceRef\": {\"Source\": \"s\"}}, \"Property\": \"Profit Margin\"}, \"Name\": \"Sales.Profit Margin\", \"NativeReferenceName\": \"Profit Margin\"}]}",
          "dataTransforms": "{}"
        },
        {
          "config": "{\"name\": \"0e7917e6-a068-48d0-a48c-ab273d7b7f12\", \"layouts\": [{\"id\": 0, \"position\": {\"x\": 700, \"y\": 30, \"z\": 1, \"width\": 450, \"height\": 310, \"tabOrder\": 1}}], \"singleVisual\": {\"visualType\": \"barChart\", \"projections\": {\"Category\": [{\"queryRef\": \"Sales.ProductName\", \"active\": true}], \"Y\": [{\"queryRef\": \"Sales.Total Revenue\"}]}, \"prototypeQuery\": {\"Version\": 2, \"From\": [{\"Name\": \"s\", \"Entity\": \"Sales\", \"Type\": 0}], \"Select\": [{\"Column\": {\"Expression\": {\"SourceRef\": {\"Source\": \"s\"}}, \"Property\": \"ProductName\"}, \"Name\": \"Sales.ProductName\", \"NativeReferenceName\": \"ProductName\"}, {\"Measure\": {\"Expression\": {\"SourceRef\": {\"Source\": \"s\"}}, \"Property\": \"Total Revenue\"}, \"Name\": \"Sales.Total Revenue\", \"NativeReferenceName\": \"Total Revenue\"}]}, \"drillFilterOtherVisuals\": true, \"hasDefaultSort\": true, \"objects\": {}, \"vcObjects\": {\"title\": [{\"properties\": {\"text\": {\"expr\": {\"Literal\": {\"Value\": \"'Top 10 Products by Revenue'\"}}}, \"show\": {\"expr\": {\"Literal\": {\"Value\": \"true\"}}}}}]}}}",
          "query": "{\"Version\": 2, \"From\": [{\"Name\": \"s\", \"Entity\": \"Sales\", \"Type\": 0}], \"Select\": [{\"Column\": {\"Expression\": {\"SourceRef\": {\"Source\": \"s\"}}, \"Property\": \"ProductName\"}, \"Name\": \"Sales.ProductName\", \"NativeReferenceName\": \"ProductName\"}, {\"Measure\": {\"Expression\": {\"SourceRef\": {\"Source\": \"s\"}}, \"Property\": \"Total Revenue\"}, \"Name\": \"Sales.Total Revenue\", \"NativeReferenceName\": \"Total Revenue\"}]}",
          "dataTransforms": "{}"
        },
        {
          "config": "{\"name\": \"a8953bf0-d6ad-44c7-a338-a2095cb3bd4d\", \"layouts\": [{\"id\": 0, \"position\": {\"x\": 700, \"y\": 370, \"z\": 2, \"width\": 450, \"height\": 310, \"tabOrder\": 2}}], \"singleVisual\": {\"visualType\": \"scatterChart\", \"projections\": {\"Category\": [{\"queryRef\": \"Sales.ProductName\", \"active\": true}], \"X\": [{\"queryRef\": \"Sales.Total Revenue\"}], \"Y\": [{\"queryRef\": \"Sales.Profit Margin\"}], \"Size\": [{\"queryRef\": \"Sales.Total Quantity\"}]}, \"prototypeQuery\": {\"Version\": 2, \"From\": [{\"Name\": \"s\", \"Entity\": \"Sales\", \"Type\": 0}], \"Select\": [{\"Column\": {\"Expression\": {\"SourceRef\": {\"Source\": \"s\"}}, \"Property\": \"ProductName\"}, \"Name\": \"Sales.ProductName\", \"NativeReferenceName\": \"ProductName\"}, {\"Measure\": {\"Expression\": {\"SourceRef\": {\"Source\": \"s\"}}, \"Property\": \"Total Revenue\"}, \"Name\": \"Sales.Total Revenue\", \"NativeReferenceName\": \"Total Revenue\"}, {\"Measure\": {\"Expression\": {\"SourceRef\": {\"Source\": \"s\"}}, \"Property\": \"Profit Margin\"}, \"Name\": \"Sales.Profit Margin\", \"NativeReferenceName\": \"Profit Margin\"}, {\"Measure\": {\"Expression\": {\"SourceRef\": {\"Source\": \"s\"}}, \"Property\": \"Total Quantity\"}, \"Name\": \"Sales.Total Quantity\", \"NativeReferenceName\": \"Total Quantity\"}]}, \"drillFilterOtherVisuals\": true, \"hasDefaultSort\": true, \"objects\": {}, \"vcObjects\": {\"title\": [{\"properties\": {\"text\": {\"expr\": {\"Literal\": {\"Value\": \"'Revenue vs Margin'\"}}}, \"show\": {\"expr\": {\"Literal\": {\"Value\": \"true\"}}}}}]}}}",
          "query": "{\"Version\": 2, \"From\": [{\"Name\": \"s\", \"Entity\": \"Sales\", \"Type\": 0}], \"Select\": [{\"Column\": {\"Expression\": {\"SourceRef\": {\"Source\": \"s\"}}, \"Property\": \"ProductName\"}, \"Name\": \"Sales.ProductName\", \"NativeReferenceName\": \"ProductName\"}, {\"Measure\": {\"Expression\": {\"SourceRef\": {\"Source\": \"s\"}}, \"Property\": \"Total Revenue\"}, \"Name\": \"Sales.Total Revenue\", \"NativeReferenceName\": \"Total Revenue\"}, {\"Measure\": {\"Expression\": {\"SourceRef\": {\"Source\": \"s\"}}, \"Property\": \"Profit Margin\"}, \"Name\": \"Sales.Profit Margin\", \"NativeReferenceName\": \"Profit Margin\"}, {\"Measure\": {\"Expression\": {\"SourceRef\": {\"Source\": \"s\"}}, \"Property\": \"Total Quantity\"}, \"Name\": \"Sales.Total Quantity\", \"NativeReferenceName\": \"Total Quantity\"}]}",
          "dataTransforms": "{}"
        }
      ]
    },
    {
      "name": "CustomerAnalytics",
      "displayName": "Customer Analytics",
      "width": 1280,
      "height": 720,
      "visualContainers": [
        {
          "config": "{\"name\": \"d84e187d-11c9-4f83-88d2-76a3912ec698\", \"layouts\": [{\"id\": 0, \"position\": {\"x\": 20, \"y\": 30, \"z\": 0, \"width\": 260, \"height\": 100, \"tabOrder\": 0}}], \"singleVisual\": {\"visualType\": \"card\", \"projections\": {\"Values\": [{\"queryRef\": \"Sales.Repeat Customer\"}]}, \"prototypeQuery\": {\"Version\": 2, \"From\": [{\"Name\": \"s\", \"Entity\": \"Sales\", \"Type\": 0}], \"Select\": [{\"Measure\": {\"Expression\": {\"SourceRef\": {\"Source\": \"s\"}}, \"Property\": \"Repeat Customer\"}, \"Name\": \"Sales.Repeat Customer\", \"NativeReferenceName\": \"Repeat Customer\"}]}, \"drillFilterOtherVisuals\": true, \"hasDefaultSort\": true, \"objects\": {}, \"vcObjects\": {\"title\": [{\"properties\": {\"text\": {\"expr\": {\"Literal\": {\"Value\": \"'Repeat Customer'\"}}}, \"show\": {\"expr\": {\"Literal\": {\"Value\": \"true\"}}}}}]}}}",
          "query": "{\"Version\": 2, \"From\": [{\"Name\": \"s\", \"Entity\": \"Sales\", \"Type\": 0}], \"Select\": [{\"Measure\": {\"Expression\": {\"SourceRef\": {\"Source\": \"s\"}}, \"Property\": \"Repeat Customer\"}, \"Name\": \"Sales.Repeat Customer\", \"NativeReferenceName\": \"Repeat Customer\"}]}",
          "dataTransforms": "{}"
        },
        {
          "config": "{\"name\": \"0b3d2ce0-06c4-4375-81d0-04433113e257\", \"layouts\": [{\"id\": 0, \"position\": {\"x\": 310, \"y\": 30, \"z\": 1, \"width\": 260, \"height\": 100, \"tabOrder\": 1}}], \"singleVisual\": {\"visualType\": \"card\", \"projections\": {\"Values\": [{\"queryRef\": \"Sales.Customer Count\"}]}, \"prototypeQuery\": {\"Version\": 2, \"From\": [{\"Name\": \"s\", \"Entity\": \"Sales\", \"Type\": 0}], \"Select\": [{\"Measure\": {\"Expression\": {\"SourceRef\": {\"Source\": \"s\"}}, \"Property\": \"Customer Count\"}, \"Name\": \"Sales.Customer Count\", \"NativeReferenceName\": \"Customer Count\"}]}, \"drillFilterOtherVisuals\": true, \"hasDefaultSort\": true, \"objects\": {}, \"vcObjects\": {\"title\": [{\"properties\": {\"text\": {\"expr\": {\"Literal\": {\"Value\": \"'Customer Count'\"}}}, \"show\": {\"expr\": {\"Literal\": {\"Value\": \"true\"}}}}}]}}}",
          "query": "{\"Version\": 2, \"From\": [{\"Name\": \"s\", \"Entity\": \"Sales\", \"Type\": 0}], \"Select\": [{\"Measure\": {\"Expression\": {\"SourceRef\": {\"Source\": \"s\"}}, \"Property\": \"Customer Count\"}, \"Name\": \"Sales.Customer Count\", \"NativeReferenceName\": \"Customer Count\"}]}",
          "dataTransforms": "{}"
        },
        {
          "config": "{\"name\": \"e29d6de6-bf55-4373-8f49-a28513e937af\", \"layouts\": [{\"id\": 0, \"position\": {\"x\": 600, \"y\": 30, \"z\": 2, \"width\": 260, \"height\": 100, \"tabOrder\": 2}}], \"singleVisual\": {\"visualType\": \"card\", \"projections\": {\"Values\": [{\"queryRef\": \"Sales.Avg Customer Spend\"}]}, \"prototypeQuery\": {\"Version\": 2, \"From\": [{\"Name\": \"s\", \"Entity\": \"Sales\", \"Type\": 0}], \"Select\": [{\"Measure\": {\"Expression\": {\"SourceRef\": {\"Source\": \"s\"}}, \"Property\": \"Avg Customer Spend\"}, \"Name\": \"Sales.Avg Customer Spend\", \"NativeReferenceName\": \"Avg Customer Spend\"}]}, \"drillFilterOtherVisuals\": true, \"hasDefaultSort\": true, \"objects\": {}, \"vcObjects\": {\"title\": [{\"properties\": {\"text\": {\"expr\": {\"Literal\": {\"Value\": \"'Avg Customer Spend'\"}}}, \"show\": {\"expr\": {\"Literal\": {\"Value\": \"true\"}}}}}]}}}",
          "query": "{\"Version\": 2, \"From\": [{\"Name\": \"s\", \"Entity\": \"Sales\", \"Type\": 0}], \"Select\": [{\"Measure\": {\"Expression\": {\"SourceRef\": {\"Source\": \"s\"}}, \"Property\": \"Avg Customer Spend\"}, \"Name\": \"Sales.Avg Customer Spend\", \"NativeReferenceName\": \"Avg Customer Spend\"}]}",
          "dataTransforms": "{}"
        },
        {
          "config": "{\"name\": \"13964964-c271-4b17-8515-a18c3af72b15\", \"layouts\": [{\"id\": 0, \"position\": {\"x\": 20, \"y\": 165, \"z\": 3, \"width\": 560, \"height\": 300, \"tabOrder\": 3}}], \"singleVisual\": {\"visualType\": \"barChart\", \"projections\": {\"Category\": [{\"queryRef\": \"Sales.Segment\", \"active\": true}], \"Y\": [{\"queryRef\": \"Sales.Total Revenue\"}]}, \"prototypeQuery\": {\"Version\": 2, \"From\": [{\"Name\": \"s\", \"Entity\": \"Sales\", \"Type\": 0}], \"Select\": [{\"Column\": {\"Expression\": {\"SourceRef\": {\"Source\": \"s\"}}, \"Property\": \"Segment\"}, \"Name\": \"Sales.Segment\", \"NativeReferenceName\": \"Segment\"}, {\"Measure\": {\"Expression\": {\"SourceRef\": {\"Source\": \"s\"}}, \"Property\": \"Total Revenue\"}, \"Name\": \"Sales.Total Revenue\", \"NativeReferenceName\": \"Total Revenue\"}]}, \"drillFilterOtherVisuals\": true, \"hasDefaultSort\": true, \"objects\": {}, \"vcObjects\": {\"title\": [{\"properties\": {\"text\": {\"expr\": {\"Literal\": {\"Value\": \"'Segment Analysis'\"}}}, \"show\": {\"expr\": {\"Literal\": {\"Value\": \"true\"}}}}}]}}}",
          "query": "{\"Version\": 2, \"From\": [{\"Name\": \"s\", \"Entity\": \"Sales\", \"Type\": 0}], \"Select\": [{\"Column\": {\"Expression\": {\"SourceRef\": {\"Source\": \"s\"}}, \"Property\": \"Segment\"}, \"Name\": \"Sales.Segment\", \"NativeReferenceName\": \"Segment\"}, {\"Measure\": {\"Expression\": {\"SourceRef\": {\"Source\": \"s\"}}, \"Property\": \"Total Revenue\"}, \"Name\": \"Sales.Total Revenue\", \"NativeReferenceName\": \"Total Revenue\"}]}",
          "dataTransforms": "{}"
        },
        {
          "config": "{\"name\": \"050b1078-8e3d-43b7-b996-4c03e8faf338\", \"layouts\": [{\"id\": 0, \"position\": {\"x\": 620, \"y\": 165, \"z\": 4, \"width\": 520, \"height\": 300, \"tabOrder\": 4}}], \"singleVisual\": {\"visualType\": \"donutChart\", \"projections\": {\"Category\": [{\"queryRef\": \"Sales.Segment\", \"active\": true}], \"Y\": [{\"queryRef\": \"Sales.Total Revenue\"}]}, \"prototypeQuery\": {\"Version\": 2, \"From\": [{\"Name\": \"s\", \"Entity\": \"Sales\", \"Type\": 0}], \"Select\": [{\"Column\": {\"Expression\": {\"SourceRef\": {\"Source\": \"s\"}}, \"Property\": \"Segment\"}, \"Name\": \"Sales.Segment\", \"NativeReferenceName\": \"Segment\"}, {\"Measure\": {\"Expression\": {\"SourceRef\": {\"Source\": \"s\"}}, \"Property\": \"Total Revenue\"}, \"Name\": \"Sales.Total Revenue\", \"NativeReferenceName\": \"Total Revenue\"}]}, \"drillFilterOtherVisuals\": true, \"hasDefaultSort\": true, \"objects\": {}, \"vcObjects\": {\"title\": [{\"properties\": {\"text\": {\"expr\": {\"Literal\": {\"Value\": \"'Revenue Share by Segment'\"}}}, \"show\": {\"expr\": {\"Literal\": {\"Value\": \"true\"}}}}}]}}}",
          "query": "{\"Version\": 2, \"From\": [{\"Name\": \"s\", \"Entity\": \"Sales\", \"Type\": 0}], \"Select\": [{\"Column\": {\"Expression\": {\"SourceRef\": {\"Source\": \"s\"}}, \"Property\": \"Segment\"}, \"Name\": \"Sales.Segment\", \"NativeReferenceName\": \"Segment\"}, {\"Measure\": {\"Expression\": {\"SourceRef\": {\"Source\": \"s\"}}, \"Property\": \"Total Revenue\"}, \"Name\": \"Sales.Total Revenue\", \"NativeReferenceName\": \"Total Revenue\"}]}",
          "dataTransforms": "{}"
        }
      ]
    },
    {
      "name": "SalesForecast",
      "displayName": "Sales Forecast",
      "width": 1280,
      "height": 720,
      "visualContainers": [
        {
          "config": "{\"name\": \"63344e52-311d-45e8-a975-ad7fcb86382a\", \"layouts\": [{\"id\": 0, \"position\": {\"x\": 20, \"y\": 30, \"z\": 0, \"width\": 1130, \"height\": 620, \"tabOrder\": 0}}], \"singleVisual\": {\"visualType\": \"lineChart\", \"projections\": {\"Category\": [{\"queryRef\": \"Date.Date\", \"active\": true}], \"Y\": [{\"queryRef\": \"Sales.Total Revenue\"}]}, \"prototypeQuery\": {\"Version\": 2, \"From\": [{\"Name\": \"s\", \"Entity\": \"Sales\", \"Type\": 0}, {\"Name\": \"d\", \"Entity\": \"Date\", \"Type\": 0}], \"Select\": [{\"Column\": {\"Expression\": {\"SourceRef\": {\"Source\": \"d\"}}, \"Property\": \"Date\"}, \"Name\": \"Date.Date\", \"NativeReferenceName\": \"Date\"}, {\"Measure\": {\"Expression\": {\"SourceRef\": {\"Source\": \"s\"}}, \"Property\": \"Total Revenue\"}, \"Name\": \"Sales.Total Revenue\", \"NativeReferenceName\": \"Total Revenue\"}]}, \"drillFilterOtherVisuals\": true, \"hasDefaultSort\": true, \"objects\": {}, \"vcObjects\": {\"title\": [{\"properties\": {\"text\": {\"expr\": {\"Literal\": {\"Value\": \"'Sales Forecast'\"}}}, \"show\": {\"expr\": {\"Literal\": {\"Value\": \"true\"}}}}}]}}}",
          "query": "{\"Version\": 2, \"From\": [{\"Name\": \"s\", \"Entity\": \"Sales\", \"Type\": 0}, {\"Name\": \"d\", \"Entity\": \"Date\", \"Type\": 0}], \"Select\": [{\"Column\": {\"Expression\": {\"SourceRef\": {\"Source\": \"d\"}}, \"Property\": \"Date\"}, \"Name\": \"Date.Date\", \"NativeReferenceName\": \"Date\"}, {\"Measure\": {\"Expression\": {\"SourceRef\": {\"Source\": \"s\"}}, \"Property\": \"Total Revenue\"}, \"Name\": \"Sales.Total Revenue\", \"NativeReferenceName\": \"Total Revenue\"}]}",
          "dataTransforms": "{}"
        }
      ]
    }
  ]
}